cmodules/csolvermodule.c
cmodules/defs.c
cmodules/kociemba.c
cmodules/korf.c
cmodules/thistlethwaite.c
cmodules/utils.c
cube_solver/__init__.py
cube_solver/cli.py
cube_solver/csolver.cp311-win_amd64.pyd
cube_solver/defs.py
cube_solver/logger.py
cube_solver/cube/__init__.py
cube_solver/cube/cube.py
cube_solver/cube/defs.py
cube_solver/cube/enums.py
cube_solver/cube/maneuver.py
cube_solver/cube/utils.py
cube_solver/solver/__init__.py
cube_solver/solver/defs.py
cube_solver/solver/dummy.py
cube_solver/solver/kociemba.py
cube_solver/solver/korf.py
cube_solver/solver/solver.py
cube_solver/solver/thistlethwaite.py
cube_solver/solver/utils.py
cube_solver-1.1.4.dist-info/licenses/AUTHORS.rst
cube_solver-1.1.4.dist-info/licenses/LICENSE
include/defs.h
include/kociemba.h
include/korf.h
include/thistlethwaite.h
include/utils.h
cube_solver-1.1.4.dist-info/METADATA
cube_solver-1.1.4.dist-info/WHEEL
cube_solver-1.1.4.dist-info/entry_points.txt
cube_solver-1.1.4.dist-info/top_level.txt
cube_solver-1.1.4.dist-info/RECORD
