Metadata-Version: 2.4
Name: cube-solver
Version: 1.1.4
Summary: Rubik's Cube Solver
Author-email: Dave Barragan <itsdaveba@gmail.com>
Maintainer-email: Dave Barragan <itsdaveba@gmail.com>
License-Expression: MIT
Project-URL: changelog, https://github.com/itsdaveba/cube-solver/blob/main/HISTORY.rst
Project-URL: documentation, https://cube-solver.readthedocs.io
Project-URL: issues, https://github.com/itsdaveba/cube-solver/issues
Project-URL: source, https://github.com/itsdaveba/cube-solver
Keywords: rubik,cube,solver
Classifier: Development Status :: 4 - Beta
Classifier: Intended Audience :: Developers
Classifier: Operating System :: MacOS
Classifier: Operating System :: Microsoft :: Windows
Classifier: Operating System :: POSIX :: Linux
Classifier: Programming Language :: Python :: 3
Classifier: Topic :: Games/Entertainment :: Puzzle Games
Requires-Python: >=3.9
License-File: LICENSE
License-File: AUTHORS.rst
Requires-Dist: typer
Requires-Dist: numpy
Provides-Extra: dev
Requires-Dist: flake8; extra == "dev"
Requires-Dist: pytest; extra == "dev"
Requires-Dist: coverage; extra == "dev"
Provides-Extra: docs
Requires-Dist: Sphinx; extra == "docs"
Requires-Dist: sphinx_rtd_theme; extra == "docs"
Requires-Dist: watchdog; extra == "docs"
Provides-Extra: build
Requires-Dist: bump2version; extra == "build"
Requires-Dist: build; extra == "build"
Requires-Dist: twine; extra == "build"
Dynamic: license-file
